{
  "items": [
    {
      "id": "1",
      "title": "朴竺「丙午春」，是厨房给春天的回信🌿",
      "content": "最近半个多月，朴竺的厨房每天都在试菜。\n\n市场上第一批春笋到了，武义的羊肚菌也下山了。\n\n今天，终于能把这份答卷交给大家。\n\n这次春季菜单叫「丙午春」。\n\n为了留住春天的鲜气，我们用了最嫩的绍兴三年梅干菜配白皮春笋，那种脆甜和咸香交织的味道，只有这个季节才有。\n\n武义鲜羊肚菌和舞茸菇一起炖，满屋子都是山野的香气。\n\n还有一道龙井茶叶拌兰州百合。\n\n龙井的清苦和百合的粉甜，像极了春天的脾气——有点个性，但让人上瘾。\n\n春天容易犯困，我们用树番茄和水果椒熬了一碗海植汤，配赤菜燕窝，喝下去整个人都清醒了。\n\n甜品这次特别用心。\n\n酒酿沃柑酸酸甜甜，草莓白玉兰好看到舍不得吃，龙井茶冻冰凉清口。\n\n主食是豆香榄菜焗饭，四季豆、甜荚、蚕豆、美人豆，把春天的豆子们都焗进了饭里。\n\n春鲜不等人。\n\n杭州大兜路122号，预约制。\n\n来吃一顿春天吧🌿",
      "images": [
        "/data/puzhu/cover.jpg",
        "/data/puzhu/morel.jpg",
        "/data/puzhu/bamboo.jpg",
        "/data/puzhu/tea-lily.jpg",
        "/data/puzhu/drink.jpg",
        "/data/puzhu/dumpling-soup.jpg",
        "/data/puzhu/tomato-soup.jpg"
      ],
      "topic": ["朴竺植物料理", "春季菜单", "杭州素食", "米其林绿星", "植物料理", "杭州约会餐厅", "春天吃什么"],
      "publishDate": "2026-03-25 10:00",
      "likes": 0
    },
    {
      "id": "2",
      "title": "春笋与羊肚菌，是山野给餐桌的回信",
      "content": "绍兴三年陈梅干菜，配当季白皮春笋。\n\n米汤慢煮去草酸，葱油浸润两小时，陈香渗入笋的每一寸肌理。\n脆嫩清甜，咸香回甘，一口便是江南春日的魂。\n\n武义鲜羊肚菌，蜂窝肌理锁住山野鲜汁。\n灰树菇锅贴煎至焦香脆嫩，青番茄微酸提鲜，芥末籽辛香收尾。\n层层递进，每一口都是浙中山野的具象表达。\n\n春鲜不等人。\n杭州大兜路122号，预约制。",
      "images": [
        "/assets/puzhu-spring-2026/sunshoot1.jpg",
        "/assets/puzhu-spring-2026/sunshoot2.jpg",
        "/assets/puzhu-spring-2026/morchella1.jpg",
        "/assets/puzhu-spring-2026/morchella2.jpg"
      ],
      "topic": ["朴竺植物料理", "春季菜单", "春笋", "羊肚菌", "杭州素食", "时令料理", "春天吃什么"],
      "publishDate": "2026-03-25 15:00",
      "likes": 0
    },
    {
      "id": "d1",
      "title": "三道开篇，是春天的第一口🌿",
      "content": "莴苣萝卜干盏，当季脆嫩莴苣层层叠成花盏，内藏萧山三年陈萝卜干的咸香回甘。\n\n时蔬春卷，薄透春卷皮裹住海苔咸鲜，苤蓝、杭椒、黄花菜花蕊轻渍锁鲜，一口脆嫩，一口清鲜。\n\n坚果枇杷塔，甄选塘栖当季枇杷，清甜无渣，夏果榛果增香提脆，雪珠花满铺点缀，宛若盛放的春日花盏。\n\n三道小食，三种春意。",
      "images": [
        "https://img01.yzcdn.cn/upload_files/2026/03/24/Fmc1FT-XplfdFP09QsEhkzfJiygu.jpg",
        "https://img01.yzcdn.cn/upload_files/2026/03/24/FtWoj70GYP3hEPS37wai3XFP98NH.jpg",
        "https://img01.yzcdn.cn/upload_files/2026/03/24/Fi4enzhQekQR9uSbDQtTBejp4M-7.jpg",
        "https://img01.yzcdn.cn/upload_files/2026/03/24/FhLXUpr2kv-24N8j1uK3ixo6FBWj.jpg",
        "https://img01.yzcdn.cn/upload_files/2026/03/24/FiMekcbtMu57N8zhsMxr1heTODpt.jpg"
      ],
      "topic": ["朴竺植物料理", "春季菜单", "春季小食", "杭州素食", "精致摆盘", "春天吃什么"],
      "publishDate": "2026-03-26 12:00",
      "likes": 0
    },
    {
      "id": "d2",
      "title": "三年陈梅干菜，配上了今年的第一根春笋",
      "content": "绍兴三年陈香梅干菜，经传统工艺晒制发酵，咸香醇厚、陈香绵长。\n\n配当季鲜采白皮春笋，笋肉洁白脆嫩、鲜甜无渣。\n\n先用米汤将笋煮熟去除草酸，再用葱油浸泡两小时，让梅干菜的陈香完全渗入笋的肌理。\n\n笋的清甜中和梅干菜的咸鲜，咸香回甘、脆嫩入味。\n\n一口解锁江南春日的烟火与雅致。",
      "images": [
        "https://img01.yzcdn.cn/upload_files/2026/03/24/FqWB-9vyimx07F7hSx0QIcCnlgUJ.jpg",
        "https://img01.yzcdn.cn/upload_files/2026/03/24/FkEXcjq2JYAtIJmD_VKoFOKqd-PL.jpg",
        "https://img01.yzcdn.cn/upload_files/2026/03/24/FmnK3Zsqjg8vVLSgO1tUj-Q_85Ef.jpg",
        "https://img01.yzcdn.cn/upload_files/2026/03/24/FoFIDErWTgaC3kF9yZLAuATQJT35.jpg"
      ],
      "topic": ["朴竺植物料理", "春季菜单", "春笋", "梅干菜", "杭州素食", "时令料理", "江南菜"],
      "publishDate": "2026-03-27 12:00",
      "likes": 0
    },
    {
      "id": "d3",
      "title": "武义羊肚菌配龙井百合，山野与茶韵",
      "content": "武义当季鲜羊肚菌，蜂窝肌理充分锁纳鲜汁。\n搭配灰树花锅贴煎至焦香脆嫩，融合青番茄微酸清鲜、芥末籽辛香层层递进。\n\n兰州九年甜百合，以龙井茶叶为引，生烤锁住清甜脆嫩。\n杏仁龙井茶粉增香，茶油提润，茶盐提味。\n\n菌香入馔，茶韵悠长。\n山野的鲜，与江南的雅，在一席间相逢。",
      "images": [
        "https://img01.yzcdn.cn/upload_files/2026/03/24/FhjmMOUmaZ2l6f5myWGP55u4UI3T.jpg",
        "https://img01.yzcdn.cn/upload_files/2026/03/24/Fv6UxieZ6enBq3E_fVn0yd1F0ola.jpg",
        "https://img01.yzcdn.cn/upload_files/2026/03/24/Fmq7B55foR4pKA7ZD24-MCJaz3VQ.jpg",
        "https://img01.yzcdn.cn/upload_files/2026/03/24/FoTl-8IHG0WKvlUOZMNs4O5KHMu5.jpg",
        "https://img01.yzcdn.cn/upload_files/2026/03/24/FiSbUxeIny8nW2JUxrHK5GcvmN_1.jpg"
      ],
      "topic": ["朴竺植物料理", "春季菜单", "羊肚菌", "龙井百合", "杭州素食", "菌菇料理", "春天吃什么"],
      "publishDate": "2026-03-28 12:00",
      "likes": 0
    },
    {
      "id": "d4",
      "title": "椒麻菜苔与温州酱菜酿生根",
      "content": "椒麻春季菜苔，荟萃白芦笋、公节瓜花、棠梨花等山野珍蔬，轻渍快焯锁鲜。\n核心以鲜花椒提劲，融入罗勒清香与蔬菜泡沫，麻而不燥，鲜而不腻。\n\n温州酱菜酿生根，甄选薄脆生根，内馅融合温州传统腌芥菜梗、腌儿菜的咸鲜，配臭豆腐醇厚酱香，香炸而成。\n外皮金黄酥脆，内馅咸香馥郁，是浙南的味觉记忆。",
      "images": [
        "https://img01.yzcdn.cn/upload_files/2026/03/24/FhxMh4JMTxOEfb3ebSezM3j9dvzM.jpg",
        "https://img01.yzcdn.cn/upload_files/2026/03/24/Fip2otNwAj3I_Ra7binSc4G7JQtb.jpg",
        "https://img01.yzcdn.cn/upload_files/2026/03/24/Fgp4dBrIsiYav8ONhs4fxaImqeNP.jpg",
        "https://img01.yzcdn.cn/upload_files/2026/03/24/FkEGhgn3fKZ4jU5Vyf-HBZx3-ITJ.jpg",
        "https://img01.yzcdn.cn/upload_files/2026/03/24/Fo20dsPUWYmf8xoNPj_UzQ1yqNcZ.jpg"
      ],
      "topic": ["朴竺植物料理", "春季菜单", "椒麻", "温州菜", "杭州素食", "创意素食", "春天吃什么"],
      "publishDate": "2026-03-29 12:00",
      "likes": 0
    },
    {
      "id": "d5",
      "title": "树番茄海植汤与薯粉三色菜圆",
      "content": "树番茄海植汤，树番茄与儿时番茄慢熬出自然果香，十余种海洋海藻舒展柔滑本味。\n山野植萃清润入汤，花香与鲜气相融，酸甜平衡、海陆双鲜、润而不腻。\n\n薯粉三色菜圆，丽水白薯粉为皮，分别以香椿、荠菜茵陈、胡萝卜为馅，手工揉制三色菜圆。\n汤底以十余种鲜蔬慢熬六小时，清鲜醇厚。\n\n一碗温润，一颗鲜灵。",
      "images": [
        "https://img01.yzcdn.cn/upload_files/2026/03/24/ljwQ8zJyLSE5fYjRSAHkAJ1hhPrE.jpg",
        "https://img01.yzcdn.cn/upload_files/2026/03/24/FhBYxw7VBmPvb-4xCMtiMLwPGW-A.jpg",
        "https://img01.yzcdn.cn/upload_files/2026/03/24/Fj21fPA0unbI-6NkS7VL2oSJwReT.jpg",
        "https://img01.yzcdn.cn/upload_files/2026/03/24/Fo_gexF0_nrCCfxQHluGWHdDIZpj.jpg"
      ],
      "topic": ["朴竺植物料理", "春季菜单", "海植汤", "菜圆", "杭州素食", "汤品", "春天吃什么"],
      "publishDate": "2026-03-30 12:00",
      "likes": 0
    },
    {
      "id": "d6",
      "title": "春豆焗饭与水蕨菜牛油果",
      "content": "豆香榄菜焗饭，以江南香米为基底，荟萃四季豆、荷兰豆、甜荚、蚕豆、美人豆等春日鲜豆。\n红糟提香、橄榄菜增韵，慢火焗制让豆香与米香深度交融，颗颗油润入味。\n\n水蕨菜腌渍牛油果，鲜嫩水蕨菜轻腌提香，绵润牛油果柔化风味，辅以菠菜清鲜、炸土豆香脆。\n以花为饰，以鲜为引。\n\n主食与前菜，春野馈赠。",
      "images": [
        "https://img01.yzcdn.cn/upload_files/2026/03/24/FhSG4v2wQIuMmDIBQdhdrqsV5yXA.jpg",
        "https://img01.yzcdn.cn/upload_files/2026/03/24/FvbJVKjctaItWpFXy1YcYPGRitFR.jpg",
        "https://img01.yzcdn.cn/upload_files/2026/03/24/FnfEpD9JRih6AAsk84c3EIfQDJh2.jpg",
        "https://img01.yzcdn.cn/upload_files/2026/03/24/FoSenorlQdXQ4FXrtbEP2N-m5I4N.jpg",
        "https://img01.yzcdn.cn/upload_files/2026/03/24/FggU4XeLL1JPwtir9Xb0hj_4xPYR.jpg"
      ],
      "topic": ["朴竺植物料理", "春季菜单", "焗饭", "牛油果", "杭州素食", "主食", "春天吃什么"],
      "publishDate": "2026-03-31 12:00",
      "likes": 0
    },
    {
      "id": "d7",
      "title": "三道甜品，把春天凝成了甜",
      "content": "酒酿沃柑，宁波象山沃柑饱满多汁，酒酿浸润中心果肉提香，剩余果肉制成冰沙，鲜爽甜润与米香醇厚交融。\n\n草莓白玉兰，白玉兰啫喱铺垫，搭配白玉兰奶油，覆以融合草莓的马蹄糕，淋上草莓红枣汁，春天凝成了甜品。\n\n龙井茶冻，龙井清雅遇上抹茶鲜爽，裹着绵密奶香融入丝滑白巧克力，一口顺滑，一口清甘。\n\n三道甜品，三种春天。",
      "images": [
        "https://img01.yzcdn.cn/upload_files/2026/03/24/FtqkXCVjWaOC9TRORqDtBNgHNDOc.jpg",
        "https://img01.yzcdn.cn/upload_files/2026/03/24/FosClblCMai2mMKpzafTYVYPj_qL.jpg",
        "https://img01.yzcdn.cn/upload_files/2026/03/24/FmF9bsa2S3_jJBsKsoncqmFggAxq.jpg",
        "https://img01.yzcdn.cn/upload_files/2026/03/24/FjlXBajbFivkzozOdll2TJ9821Hh.jpg",
        "https://img01.yzcdn.cn/upload_files/2026/03/24/Frl5_ei_UozfimlxnrMEsgvUYacH.jpg"
      ],
      "topic": ["朴竺植物料理", "春季菜单", "甜品", "龙井茶冻", "杭州素食", "精致甜品", "春天吃什么"],
      "publishDate": "2026-04-01 12:00",
      "likes": 0
    }
  ]
}
